asyncio_extras/__init__.py
asyncio_extras/asyncyield.py
asyncio_extras/contextmanager.py
asyncio_extras/file.py
asyncio_extras/generator.py
asyncio_extras/threads.py
asyncio_extras-1.3.2.dist-info/LICENSE.txt
asyncio_extras-1.3.2.dist-info/METADATA
asyncio_extras-1.3.2.dist-info/RECORD
asyncio_extras-1.3.2.dist-info/WHEEL
asyncio_extras-1.3.2.dist-info/top_level.txt
