Metadata-Version: 2.1
Name: asyncio-extras
Version: 1.3.2
Summary: Asynchronous generators, context managers and more for asyncio
Home-page: https://github.com/agronholm/asyncio_extras
Author: Alex Grönholm
Author-email: alex.gronholm@nextday.fi
License: MIT
Project-URL: Bug Tracker, https://github.com/agronholm/asyncio_extras/issues
Project-URL: Documentation, http://asyncio-extras.readthedocs.io/
Platform: UNKNOWN
Classifier: Development Status :: 5 - Production/Stable
Classifier: Intended Audience :: Developers
Classifier: License :: OSI Approved :: MIT License
Classifier: Programming Language :: Python
Classifier: Programming Language :: Python :: 3
Classifier: Programming Language :: Python :: 3.5
Classifier: Programming Language :: Python :: 3.6
Classifier: Programming Language :: Python :: 3.7
Provides-Extra: doc
Provides-Extra: test
